{
  "id": "hero_text",
  "type": "SharedSlice",
  "name": "HeroText",
  "description": "HeroText",
  "variations": [
    {
      "id": "default",
      "name": "Default",
      "docURL": "...",
      "version": "initial",
      "description": "Default",
      "imageUrl": "",
      "primary": {
        "title": {
          "type": "StructuredText",
          "config": {
            "label": "Title",
            "placeholder": "",
            "allowTargetBlank": true,
            "single": "heading1"
          }
        },
        "subtitle": {
          "type": "StructuredText",
          "config": {
            "label": "Subtitle",
            "placeholder": "",
            "allowTargetBlank": true,
            "single": "paragraph"
          }
        }
      },
      "items": {}
    }
  ]
}